labdevices/__init__.py
labdevices/allied_vision.py
labdevices/aml.py
labdevices/ando.py
labdevices/applied_motion_products.py
labdevices/keysight.py
labdevices/kuhne_electronic.py
labdevices/newport.py
labdevices/pfeiffer_vacuum.py
labdevices/rohde_schwarz.py
labdevices/stanford_research_systems.py
labdevices/thorlabs.py
labdevices/_mock/__init__.py
labdevices/_mock/allied_vision.py
labdevices/_mock/ando.py
labdevices/_mock/applied_motion_products.py
labdevices/_mock/keysight.py
labdevices/_mock/kuhne_electronic.py
labdevices/_mock/newport.py
labdevices/_mock/pfeiffer_vacuum.py
labdevices/_mock/rohde_schwarz.py
labdevices/_mock/stanford_research_systems.py
labdevices/_mock/thorlabs.py
labdevices/_mock/data/allied_vision_frame.pickle
labdevices/_mock/data/keysight_oscilloscope_screenshot.png
labdevices/_mock/data/keysight_oscilloscope_trace_bin
labdevices/_mock/data/rohde_schwarz_oscilloscope_screenshot.png
labdevices/_mock/data/rohde_schwarz_oscilloscope_trace.txt
labdevices/_mock/data/rohde_schwarz_spectrum_analyzer_trace.txt
labdevices-0.10.2.dist-info/LICENSE.md
labdevices-0.10.2.dist-info/METADATA
labdevices-0.10.2.dist-info/WHEEL
labdevices-0.10.2.dist-info/top_level.txt
labdevices-0.10.2.dist-info/RECORD
