Metadata-Version: 2.1
Name: labdevices
Version: 0.10.2
Summary: SDK for typical devices found in an atomic physics research lab.
Home-page: https://github.com/jkrauth/labdevices
Author: Julian Krauth
Author-email: j.krauth@vu.nl
License: MIT
Platform: UNKNOWN
Classifier: License :: OSI Approved :: MIT License
Classifier: Programming Language :: Python :: 3
Classifier: Topic :: Scientific/Engineering :: Physics
Classifier: Intended Audience :: Science/Research
Requires-Python: >=3.6
Requires-Dist: numpy
Requires-Dist: pymba
Requires-Dist: pyusb
Requires-Dist: pyserial
Requires-Dist: PyVISA
Requires-Dist: PyVISA-py
